<?xml version="1.0" ?><loginpagebantal.ArrayList><arrayList><loginpagebantal.Konsultasi><alamat>Jl.Barbasari no.5(Dr.Fahni)</alamat><tanggalhari>2022-07-02</tanggalhari><waktu>14.00 - 15.15</waktu><tatapmuka>iya</tatapmuka><keluhan>km</keluhan></loginpagebantal.Konsultasi><loginpagebantal.Konsultasi><alamat>Jl.Barbasari no.5(Dr.Fahni)</alamat><tanggalhari>2022-07-02</tanggalhari><waktu>14.00 - 15.15</waktu><tatapmuka>iya</tatapmuka><keluhan>mjnjnjn</keluhan></loginpagebantal.Konsultasi><loginpagebantal.Konsultasi><alamat>Jl.nglanjaran no.3 (Dr.Vahri)</alamat><tanggalhari>2022-07-02</tanggalhari><waktu>09.00 - 10.35</waktu><tatapmuka>iya</tatapmuka><keluhan>ga</keluhan></loginpagebantal.Konsultasi><null></null><null></null><null></null><null></null><null></null><null></null><null></null></arrayList><size>3</size></loginpagebantal.ArrayList>